alphadb-1.0.0.dist-info/METADATA
alphadb-1.0.0.dist-info/WHEEL
alphadb-1.0.0.dist-info/licenses/LICENSE
alphadb.libs/libcrypto-8173d9ca.so.3
alphadb.libs/libssl-fa9d51fe.so.3
alphadb/__init__.py
alphadb/__init__.pyi
alphadb/py.typed
alphadb/alphadb.cpython-312-x86_64-linux-gnu.so
alphadb-1.0.0.dist-info/RECORD
