Metadata-Version: 2.4
Name: alphadb
Version: 1.0.0
Classifier: Programming Language :: Rust
Classifier: Programming Language :: Python :: Implementation :: CPython
Classifier: Programming Language :: Python :: Implementation :: PyPy
Classifier: License :: OSI Approved :: GNU General Public License v3 or later (GPLv3+)
Classifier: Operating System :: OS Independent
Classifier: Programming Language :: Python :: 3 :: Only
License-File: LICENSE
Summary: AlphaDB is a versatile tool for managing MySQL database versions, using JSON to define structures and simplify migrations across environments.
Keywords: database,rust,extension,mysql database management,mysql version management,database migration tool,database version management
Home-Page: https://alphadb.w-kuipers.com
License: GPL-3.0
Requires-Python: >=3.8
Project-URL: Documentation, https://alphadb.w-kuipers.com
Project-URL: Repository, https://github.com/w-kuipers/alphadb
Project-URL: Bug Tracker, https://github.com/w-kuipers/alphadb/issues
